gerbertools/__init__.py
gerbertools/__main__.py
gerbertools/_gerbertools.cpython-36m-darwin.so
gerbertools-0.1.0.dist-info/LICENSE
gerbertools-0.1.0.dist-info/METADATA
gerbertools-0.1.0.dist-info/WHEEL
gerbertools-0.1.0.dist-info/entry_points.txt
gerbertools-0.1.0.dist-info/top_level.txt
gerbertools-0.1.0.dist-info/RECORD
