Metadata-Version: 2.1
Name: gerbertools
Version: 0.1.0
Summary: Tools for inspecting and DRC'ing PCBs their Gerber files
Home-page: https://github.com/jvanstraten/gerbertools
Author: Jeroen van Straten
License: UNKNOWN
Platform: UNKNOWN
Classifier: License :: OSI Approved :: MIT License
Classifier: Operating System :: POSIX :: Linux
Classifier: Programming Language :: Python :: 3 :: Only
Classifier: Topic :: Scientific/Engineering
License-File: LICENSE
Requires-Dist: msvc-runtime ; platform_system == "Windows"
